BirdBrain.py
birdbrain_python_library/__init__.py
birdbrain_python_library/__main__.py
birdbrain_python_library/cli.py
birdbrain_python_library-0.0.12.dist-info/licenses/AUTHORS.rst
birdbrain_python_library-0.0.12.dist-info/licenses/LICENSE
birdbrain_python_library-0.0.12.dist-info/METADATA
birdbrain_python_library-0.0.12.dist-info/WHEEL
birdbrain_python_library-0.0.12.dist-info/entry_points.txt
birdbrain_python_library-0.0.12.dist-info/top_level.txt
birdbrain_python_library-0.0.12.dist-info/RECORD
