Metadata-Version: 2.4
Name: birdbrain-python-library
Version: 0.0.12
Summary: Python Library for Birdbrain Technologies Hummingbird Bit and Finch 2
Home-page: https://github.com/fmorton/BirdBrain-Python-Library
Author: Frank Morton
Author-email: fmorton@base2inc.com
License: LGPL-3.0-only
Project-URL: Hummingbird Docs, https://learn.birdbraintechnologies.com/hummingbirdbit/python/library/
Project-URL: Finch Docs, https://learn.birdbraintechnologies.com/finch/python/library/
Project-URL: Source, https://github.com/fmorton/BirdBrain-Python-Library
Project-URL: Issue Tracker, https://github.com/fmorton/BirdBrain-Python-Library/issues
Classifier: Development Status :: 5 - Production/Stable
Classifier: Intended Audience :: Developers
Classifier: License :: OSI Approved :: GNU Lesser General Public License v3 (LGPLv3)
Classifier: Operating System :: Unix
Classifier: Operating System :: POSIX
Classifier: Operating System :: Microsoft :: Windows
Classifier: Programming Language :: Python
Classifier: Programming Language :: Python :: 3
Classifier: Programming Language :: Python :: 3 :: Only
Classifier: Programming Language :: Python :: 3.7
Classifier: Programming Language :: Python :: 3.8
Classifier: Programming Language :: Python :: 3.9
Classifier: Programming Language :: Python :: 3.10
Classifier: Programming Language :: Python :: Implementation :: CPython
Classifier: Programming Language :: Python :: Implementation :: PyPy
Classifier: Topic :: Utilities
Requires-Python: >=3.7
License-File: LICENSE
License-File: AUTHORS.rst
Dynamic: author
Dynamic: author-email
Dynamic: classifier
Dynamic: description
Dynamic: home-page
Dynamic: license
Dynamic: license-file
Dynamic: project-url
Dynamic: requires-python
Dynamic: summary
